Metadata-Version: 1.0
Name: async-chat-client-kd
Version: 0.1
Summary: chat_client
Home-page: UNKNOWN
Author: Dmitry K
Author-email: k-d@bk.ru
License: UNKNOWN
Platform: UNKNOWN
